{"name": "Heady Memory Enforcer", "version": "1.0.0", "description": "Forces Windsurf to ALWAYS scan HeadyMemory before any operation", "enforce": {"pre_operation_hooks": [{"trigger": "before_code_generation", "action": "scan_heady_memory", "mandatory": true, "timeout_ms": 3000}, {"trigger": "before_file_edit", "action": "load_context_from_memory", "mandatory": true, "timeout_ms": 2000}, {"trigger": "before_response", "action": "query_memory_for_patterns", "mandatory": true, "timeout_ms": 1500}], "post_operation_hooks": [{"trigger": "after_code_generation", "action": "ingest_to_memory", "mandatory": true}, {"trigger": "after_conversation_turn", "action": "save_conversation_context", "mandatory": true}]}, "memory_integration": {"primary_backend": "HeadyMemory", "fallback_backend": "sqlite", "query_on_startup": true, "continuous_learning": true, "cache_warmup": true}}
